django_retention_policy/__init__.py
django_retention_policy-0.1.1.dist-info/LICENSE
django_retention_policy-0.1.1.dist-info/METADATA
django_retention_policy-0.1.1.dist-info/WHEEL
django_retention_policy-0.1.1.dist-info/top_level.txt
django_retention_policy-0.1.1.dist-info/RECORD
