Metadata-Version: 2.1
Name: django-retention-policy
Version: 0.1.1
Summary: A Django Management Command to rename existing Django Applications.
Home-page: https://github.com/odwyersoftware/django-retention-policy
Author: O'Dwyer Software
Author-email: hello@odwyer.software
License: Apache 2.0
Platform: UNKNOWN
Classifier: Intended Audience :: Developers
Classifier: Operating System :: OS Independent
Classifier: Programming Language :: Python
Classifier: Programming Language :: Python :: 3
Requires-Dist: django
Requires-Dist: celery
